geotile/GeoTile.py
geotile/__init__.py
geotile/__version__.py
geotile/utils.py
geotile-1.1.0.dist-info/LICENSE
geotile-1.1.0.dist-info/METADATA
geotile-1.1.0.dist-info/WHEEL
geotile-1.1.0.dist-info/top_level.txt
geotile-1.1.0.dist-info/RECORD
